{
  "status": true,
  "data": {
    "id": "1422",
    "lokasi": "KAB. REMBANG",
    "daerah": "JAWA TENGAH",
    "koordinat": {
      "lat": -6.705708333333334,
      "lon": 111.34786944444444,
      "lintang": "6\u00b0 42' 20.55\" S",
      "bujur": "111\u00b0 20' 52.33\" E"
    },
    "jadwal": [
      {
        "tanggal": "Rabu, 01/12/2021",
        "imsak": "03:37",
        "subuh": "03:47",
        "terbit": "05:06",
        "dhuha": "05:35",
        "dzuhur": "11:27",
        "ashar": "14:52",
        "maghrib": "17:41",
        "isya": "18:56",
        "date": "2021-12-01"
      },
      {
        "tanggal": "Kamis, 02/12/2021",
        "imsak": "03:37",
        "subuh": "03:47",
        "terbit": "05:06",
        "dhuha": "05:35",
        "dzuhur": "11:27",
        "ashar": "14:52",
        "maghrib": "17:42",
        "isya": "18:57",
        "date": "2021-12-02"
      },
      {
        "tanggal": "Jumat, 03/12/2021",
        "imsak": "03:38",
        "subuh": "03:48",
        "terbit": "05:06",
        "dhuha": "05:35",
        "dzuhur": "11:28",
        "ashar": "14:53",
        "maghrib": "17:42",
        "isya": "18:57",
        "date": "2021-12-03"
      },
      {
        "tanggal": "Sabtu, 04/12/2021",
        "imsak": "03:38",
        "subuh": "03:48",
        "terbit": "05:07",
        "dhuha": "05:36",
        "dzuhur": "11:28",
        "ashar": "14:53",
        "maghrib": "17:43",
        "isya": "18:58",
        "date": "2021-12-04"
      },
      {
        "tanggal": "Minggu, 05/12/2021",
        "imsak": "03:38",
        "subuh": "03:48",
        "terbit": "05:07",
        "dhuha": "05:36",
        "dzuhur": "11:29",
        "ashar": "14:54",
        "maghrib": "17:43",
        "isya": "18:58",
        "date": "2021-12-05"
      },
      {
        "tanggal": "Senin, 06/12/2021",
        "imsak": "03:38",
        "subuh": "03:48",
        "terbit": "05:07",
        "dhuha": "05:36",
        "dzuhur": "11:29",
        "ashar": "14:54",
        "maghrib": "17:44",
        "isya": "18:59",
        "date": "2021-12-06"
      },
      {
        "tanggal": "Selasa, 07/12/2021",
        "imsak": "03:39",
        "subuh": "03:49",
        "terbit": "05:08",
        "dhuha": "05:37",
        "dzuhur": "11:30",
        "ashar": "14:55",
        "maghrib": "17:44",
        "isya": "19:00",
        "date": "2021-12-07"
      },
      {
        "tanggal": "Rabu, 08/12/2021",
        "imsak": "03:39",
        "subuh": "03:49",
        "terbit": "05:08",
        "dhuha": "05:37",
        "dzuhur": "11:30",
        "ashar": "14:56",
        "maghrib": "17:45",
        "isya": "19:00",
        "date": "2021-12-08"
      },
      {
        "tanggal": "Kamis, 09/12/2021",
        "imsak": "03:39",
        "subuh": "03:49",
        "terbit": "05:09",
        "dhuha": "05:38",
        "dzuhur": "11:30",
        "ashar": "14:56",
        "maghrib": "17:45",
        "isya": "19:01",
        "date": "2021-12-09"
      },
      {
        "tanggal": "Jumat, 10/12/2021",
        "imsak": "03:39",
        "subuh": "03:49",
        "terbit": "05:09",
        "dhuha": "05:38",
        "dzuhur": "11:31",
        "ashar": "14:57",
        "maghrib": "17:46",
        "isya": "19:01",
        "date": "2021-12-10"
      },
      {
        "tanggal": "Sabtu, 11/12/2021",
        "imsak": "03:40",
        "subuh": "03:50",
        "terbit": "05:09",
        "dhuha": "05:38",
        "dzuhur": "11:31",
        "ashar": "14:57",
        "maghrib": "17:46",
        "isya": "19:02",
        "date": "2021-12-11"
      },
      {
        "tanggal": "Minggu, 12/12/2021",
        "imsak": "03:40",
        "subuh": "03:50",
        "terbit": "05:10",
        "dhuha": "05:39",
        "dzuhur": "11:32",
        "ashar": "14:58",
        "maghrib": "17:47",
        "isya": "19:02",
        "date": "2021-12-12"
      },
      {
        "tanggal": "Senin, 13/12/2021",
        "imsak": "03:41",
        "subuh": "03:51",
        "terbit": "05:10",
        "dhuha": "05:39",
        "dzuhur": "11:32",
        "ashar": "14:58",
        "maghrib": "17:47",
        "isya": "19:03",
        "date": "2021-12-13"
      },
      {
        "tanggal": "Selasa, 14/12/2021",
        "imsak": "03:41",
        "subuh": "03:51",
        "terbit": "05:11",
        "dhuha": "05:40",
        "dzuhur": "11:33",
        "ashar": "14:59",
        "maghrib": "17:48",
        "isya": "19:03",
        "date": "2021-12-14"
      },
      {
        "tanggal": "Rabu, 15/12/2021",
        "imsak": "03:41",
        "subuh": "03:51",
        "terbit": "05:11",
        "dhuha": "05:40",
        "dzuhur": "11:33",
        "ashar": "14:59",
        "maghrib": "17:48",
        "isya": "19:04",
        "date": "2021-12-15"
      },
      {
        "tanggal": "Kamis, 16/12/2021",
        "imsak": "03:42",
        "subuh": "03:52",
        "terbit": "05:12",
        "dhuha": "05:41",
        "dzuhur": "11:34",
        "ashar": "15:00",
        "maghrib": "17:49",
        "isya": "19:05",
        "date": "2021-12-16"
      },
      {
        "tanggal": "Jumat, 17/12/2021",
        "imsak": "03:42",
        "subuh": "03:52",
        "terbit": "05:12",
        "dhuha": "05:41",
        "dzuhur": "11:34",
        "ashar": "15:00",
        "maghrib": "17:49",
        "isya": "19:05",
        "date": "2021-12-17"
      },
      {
        "tanggal": "Sabtu, 18/12/2021",
        "imsak": "03:43",
        "subuh": "03:53",
        "terbit": "05:12",
        "dhuha": "05:42",
        "dzuhur": "11:35",
        "ashar": "15:01",
        "maghrib": "17:50",
        "isya": "19:06",
        "date": "2021-12-18"
      },
      {
        "tanggal": "Minggu, 19/12/2021",
        "imsak": "03:43",
        "subuh": "03:53",
        "terbit": "05:13",
        "dhuha": "05:42",
        "dzuhur": "11:35",
        "ashar": "15:01",
        "maghrib": "17:50",
        "isya": "19:06",
        "date": "2021-12-19"
      },
      {
        "tanggal": "Senin, 20/12/2021",
        "imsak": "03:44",
        "subuh": "03:54",
        "terbit": "05:13",
        "dhuha": "05:43",
        "dzuhur": "11:36",
        "ashar": "15:02",
        "maghrib": "17:51",
        "isya": "19:07",
        "date": "2021-12-20"
      },
      {
        "tanggal": "Selasa, 21/12/2021",
        "imsak": "03:44",
        "subuh": "03:54",
        "terbit": "05:14",
        "dhuha": "05:43",
        "dzuhur": "11:36",
        "ashar": "15:03",
        "maghrib": "17:51",
        "isya": "19:07",
        "date": "2021-12-21"
      },
      {
        "tanggal": "Rabu, 22/12/2021",
        "imsak": "03:45",
        "subuh": "03:55",
        "terbit": "05:14",
        "dhuha": "05:44",
        "dzuhur": "11:37",
        "ashar": "15:03",
        "maghrib": "17:52",
        "isya": "19:08",
        "date": "2021-12-22"
      },
      {
        "tanggal": "Kamis, 23/12/2021",
        "imsak": "03:45",
        "subuh": "03:55",
        "terbit": "05:15",
        "dhuha": "05:44",
        "dzuhur": "11:37",
        "ashar": "15:04",
        "maghrib": "17:52",
        "isya": "19:08",
        "date": "2021-12-23"
      },
      {
        "tanggal": "Jumat, 24/12/2021",
        "imsak": "03:46",
        "subuh": "03:56",
        "terbit": "05:15",
        "dhuha": "05:45",
        "dzuhur": "11:38",
        "ashar": "15:04",
        "maghrib": "17:53",
        "isya": "19:09",
        "date": "2021-12-24"
      },
      {
        "tanggal": "Sabtu, 25/12/2021",
        "imsak": "03:46",
        "subuh": "03:56",
        "terbit": "05:16",
        "dhuha": "05:45",
        "dzuhur": "11:38",
        "ashar": "15:04",
        "maghrib": "17:53",
        "isya": "19:09",
        "date": "2021-12-25"
      },
      {
        "tanggal": "Minggu, 26/12/2021",
        "imsak": "03:47",
        "subuh": "03:57",
        "terbit": "05:16",
        "dhuha": "05:46",
        "dzuhur": "11:39",
        "ashar": "15:05",
        "maghrib": "17:54",
        "isya": "19:09",
        "date": "2021-12-26"
      },
      {
        "tanggal": "Senin, 27/12/2021",
        "imsak": "03:47",
        "subuh": "03:57",
        "terbit": "05:17",
        "dhuha": "05:46",
        "dzuhur": "11:39",
        "ashar": "15:05",
        "maghrib": "17:54",
        "isya": "19:10",
        "date": "2021-12-27"
      },
      {
        "tanggal": "Selasa, 28/12/2021",
        "imsak": "03:48",
        "subuh": "03:58",
        "terbit": "05:17",
        "dhuha": "05:47",
        "dzuhur": "11:40",
        "ashar": "15:06",
        "maghrib": "17:55",
        "isya": "19:10",
        "date": "2021-12-28"
      },
      {
        "tanggal": "Rabu, 29/12/2021",
        "imsak": "03:48",
        "subuh": "03:58",
        "terbit": "05:18",
        "dhuha": "05:47",
        "dzuhur": "11:40",
        "ashar": "15:06",
        "maghrib": "17:55",
        "isya": "19:11",
        "date": "2021-12-29"
      },
      {
        "tanggal": "Kamis, 30/12/2021",
        "imsak": "03:49",
        "subuh": "03:59",
        "terbit": "05:18",
        "dhuha": "05:48",
        "dzuhur": "11:41",
        "ashar": "15:07",
        "maghrib": "17:56",
        "isya": "19:11",
        "date": "2021-12-30"
      },
      {
        "tanggal": "Jumat, 31/12/2021",
        "imsak": "03:49",
        "subuh": "03:59",
        "terbit": "05:19",
        "dhuha": "05:48",
        "dzuhur": "11:41",
        "ashar": "15:07",
        "maghrib": "17:56",
        "isya": "19:12",
        "date": "2021-12-31"
      }
    ]
  }
}