{
  "status": true,
  "data": {
    "id": "0603",
    "lokasi": "KAB. KERINCI",
    "daerah": "JAMBI",
    "koordinat": {
      "lat": -1.9679222222222221,
      "lon": 101.35619444444444,
      "lintang": "1\u00b0 58' 4.52\" S",
      "bujur": "101\u00b0 21' 22.3\" E"
    },
    "jadwal": [
      {
        "tanggal": "Rabu, 01/11/2023",
        "imsak": "04:26",
        "subuh": "04:36",
        "terbit": "05:45",
        "dhuha": "06:17",
        "dzuhur": "12:02",
        "ashar": "15:20",
        "maghrib": "18:11",
        "isya": "19:17",
        "date": "2023-11-01"
      },
      {
        "tanggal": "Kamis, 02/11/2023",
        "imsak": "04:26",
        "subuh": "04:36",
        "terbit": "05:45",
        "dhuha": "06:17",
        "dzuhur": "12:02",
        "ashar": "15:20",
        "maghrib": "18:11",
        "isya": "19:17",
        "date": "2023-11-02"
      },
      {
        "tanggal": "Jumat, 03/11/2023",
        "imsak": "04:25",
        "subuh": "04:35",
        "terbit": "05:45",
        "dhuha": "06:17",
        "dzuhur": "12:02",
        "ashar": "15:20",
        "maghrib": "18:11",
        "isya": "19:18",
        "date": "2023-11-03"
      },
      {
        "tanggal": "Sabtu, 04/11/2023",
        "imsak": "04:25",
        "subuh": "04:35",
        "terbit": "05:45",
        "dhuha": "06:17",
        "dzuhur": "12:02",
        "ashar": "15:20",
        "maghrib": "18:11",
        "isya": "19:18",
        "date": "2023-11-04"
      },
      {
        "tanggal": "Minggu, 05/11/2023",
        "imsak": "04:25",
        "subuh": "04:35",
        "terbit": "05:45",
        "dhuha": "06:17",
        "dzuhur": "12:02",
        "ashar": "15:21",
        "maghrib": "18:11",
        "isya": "19:18",
        "date": "2023-11-05"
      },
      {
        "tanggal": "Senin, 06/11/2023",
        "imsak": "04:25",
        "subuh": "04:35",
        "terbit": "05:45",
        "dhuha": "06:17",
        "dzuhur": "12:02",
        "ashar": "15:21",
        "maghrib": "18:11",
        "isya": "19:18",
        "date": "2023-11-06"
      },
      {
        "tanggal": "Selasa, 07/11/2023",
        "imsak": "04:25",
        "subuh": "04:35",
        "terbit": "05:45",
        "dhuha": "06:17",
        "dzuhur": "12:02",
        "ashar": "15:21",
        "maghrib": "18:11",
        "isya": "19:18",
        "date": "2023-11-07"
      },
      {
        "tanggal": "Rabu, 08/11/2023",
        "imsak": "04:25",
        "subuh": "04:35",
        "terbit": "05:45",
        "dhuha": "06:17",
        "dzuhur": "12:02",
        "ashar": "15:22",
        "maghrib": "18:11",
        "isya": "19:19",
        "date": "2023-11-08"
      },
      {
        "tanggal": "Kamis, 09/11/2023",
        "imsak": "04:25",
        "subuh": "04:35",
        "terbit": "05:45",
        "dhuha": "06:17",
        "dzuhur": "12:02",
        "ashar": "15:22",
        "maghrib": "18:12",
        "isya": "19:19",
        "date": "2023-11-09"
      },
      {
        "tanggal": "Jumat, 10/11/2023",
        "imsak": "04:24",
        "subuh": "04:34",
        "terbit": "05:45",
        "dhuha": "06:17",
        "dzuhur": "12:02",
        "ashar": "15:23",
        "maghrib": "18:12",
        "isya": "19:19",
        "date": "2023-11-10"
      },
      {
        "tanggal": "Sabtu, 11/11/2023",
        "imsak": "04:24",
        "subuh": "04:34",
        "terbit": "05:45",
        "dhuha": "06:17",
        "dzuhur": "12:02",
        "ashar": "15:23",
        "maghrib": "18:12",
        "isya": "19:19",
        "date": "2023-11-11"
      },
      {
        "tanggal": "Minggu, 12/11/2023",
        "imsak": "04:24",
        "subuh": "04:34",
        "terbit": "05:45",
        "dhuha": "06:18",
        "dzuhur": "12:02",
        "ashar": "15:23",
        "maghrib": "18:12",
        "isya": "19:20",
        "date": "2023-11-12"
      },
      {
        "tanggal": "Senin, 13/11/2023",
        "imsak": "04:24",
        "subuh": "04:34",
        "terbit": "05:45",
        "dhuha": "06:18",
        "dzuhur": "12:02",
        "ashar": "15:24",
        "maghrib": "18:12",
        "isya": "19:20",
        "date": "2023-11-13"
      },
      {
        "tanggal": "Selasa, 14/11/2023",
        "imsak": "04:24",
        "subuh": "04:34",
        "terbit": "05:45",
        "dhuha": "06:18",
        "dzuhur": "12:02",
        "ashar": "15:24",
        "maghrib": "18:12",
        "isya": "19:20",
        "date": "2023-11-14"
      },
      {
        "tanggal": "Rabu, 15/11/2023",
        "imsak": "04:24",
        "subuh": "04:34",
        "terbit": "05:45",
        "dhuha": "06:18",
        "dzuhur": "12:03",
        "ashar": "15:24",
        "maghrib": "18:13",
        "isya": "19:21",
        "date": "2023-11-15"
      },
      {
        "tanggal": "Kamis, 16/11/2023",
        "imsak": "04:24",
        "subuh": "04:34",
        "terbit": "05:46",
        "dhuha": "06:18",
        "dzuhur": "12:03",
        "ashar": "15:25",
        "maghrib": "18:13",
        "isya": "19:21",
        "date": "2023-11-16"
      },
      {
        "tanggal": "Jumat, 17/11/2023",
        "imsak": "04:24",
        "subuh": "04:34",
        "terbit": "05:46",
        "dhuha": "06:18",
        "dzuhur": "12:03",
        "ashar": "15:25",
        "maghrib": "18:13",
        "isya": "19:21",
        "date": "2023-11-17"
      },
      {
        "tanggal": "Sabtu, 18/11/2023",
        "imsak": "04:24",
        "subuh": "04:34",
        "terbit": "05:46",
        "dhuha": "06:18",
        "dzuhur": "12:03",
        "ashar": "15:26",
        "maghrib": "18:13",
        "isya": "19:22",
        "date": "2023-11-18"
      },
      {
        "tanggal": "Minggu, 19/11/2023",
        "imsak": "04:24",
        "subuh": "04:34",
        "terbit": "05:46",
        "dhuha": "06:19",
        "dzuhur": "12:03",
        "ashar": "15:26",
        "maghrib": "18:14",
        "isya": "19:22",
        "date": "2023-11-19"
      },
      {
        "tanggal": "Senin, 20/11/2023",
        "imsak": "04:24",
        "subuh": "04:34",
        "terbit": "05:46",
        "dhuha": "06:19",
        "dzuhur": "12:04",
        "ashar": "15:26",
        "maghrib": "18:14",
        "isya": "19:22",
        "date": "2023-11-20"
      },
      {
        "tanggal": "Selasa, 21/11/2023",
        "imsak": "04:24",
        "subuh": "04:34",
        "terbit": "05:46",
        "dhuha": "06:19",
        "dzuhur": "12:04",
        "ashar": "15:27",
        "maghrib": "18:14",
        "isya": "19:23",
        "date": "2023-11-21"
      },
      {
        "tanggal": "Rabu, 22/11/2023",
        "imsak": "04:24",
        "subuh": "04:34",
        "terbit": "05:47",
        "dhuha": "06:19",
        "dzuhur": "12:04",
        "ashar": "15:27",
        "maghrib": "18:15",
        "isya": "19:23",
        "date": "2023-11-22"
      },
      {
        "tanggal": "Kamis, 23/11/2023",
        "imsak": "04:25",
        "subuh": "04:35",
        "terbit": "05:47",
        "dhuha": "06:20",
        "dzuhur": "12:04",
        "ashar": "15:28",
        "maghrib": "18:15",
        "isya": "19:24",
        "date": "2023-11-23"
      },
      {
        "tanggal": "Jumat, 24/11/2023",
        "imsak": "04:25",
        "subuh": "04:35",
        "terbit": "05:47",
        "dhuha": "06:20",
        "dzuhur": "12:05",
        "ashar": "15:28",
        "maghrib": "18:15",
        "isya": "19:24",
        "date": "2023-11-24"
      },
      {
        "tanggal": "Sabtu, 25/11/2023",
        "imsak": "04:25",
        "subuh": "04:35",
        "terbit": "05:47",
        "dhuha": "06:20",
        "dzuhur": "12:05",
        "ashar": "15:28",
        "maghrib": "18:15",
        "isya": "19:24",
        "date": "2023-11-25"
      },
      {
        "tanggal": "Minggu, 26/11/2023",
        "imsak": "04:25",
        "subuh": "04:35",
        "terbit": "05:48",
        "dhuha": "06:20",
        "dzuhur": "12:05",
        "ashar": "15:29",
        "maghrib": "18:16",
        "isya": "19:25",
        "date": "2023-11-26"
      },
      {
        "tanggal": "Senin, 27/11/2023",
        "imsak": "04:25",
        "subuh": "04:35",
        "terbit": "05:48",
        "dhuha": "06:21",
        "dzuhur": "12:05",
        "ashar": "15:29",
        "maghrib": "18:16",
        "isya": "19:25",
        "date": "2023-11-27"
      },
      {
        "tanggal": "Selasa, 28/11/2023",
        "imsak": "04:25",
        "subuh": "04:35",
        "terbit": "05:48",
        "dhuha": "06:21",
        "dzuhur": "12:06",
        "ashar": "15:30",
        "maghrib": "18:17",
        "isya": "19:26",
        "date": "2023-11-28"
      },
      {
        "tanggal": "Rabu, 29/11/2023",
        "imsak": "04:25",
        "subuh": "04:35",
        "terbit": "05:48",
        "dhuha": "06:21",
        "dzuhur": "12:06",
        "ashar": "15:30",
        "maghrib": "18:17",
        "isya": "19:26",
        "date": "2023-11-29"
      },
      {
        "tanggal": "Kamis, 30/11/2023",
        "imsak": "04:26",
        "subuh": "04:36",
        "terbit": "05:49",
        "dhuha": "06:22",
        "dzuhur": "12:07",
        "ashar": "15:31",
        "maghrib": "18:17",
        "isya": "19:27",
        "date": "2023-11-30"
      }
    ]
  }
}