{
  "status": true,
  "data": {
    "id": "0117",
    "lokasi": "KAB. PIDIE JAYA",
    "daerah": "ACEH",
    "koordinat": {
      "lat": 5.232938888888889,
      "lon": 96.26139722222223,
      "lintang": "5\u00b0 13' 58.58\" N",
      "bujur": "96\u00b0 15' 41.03\" E"
    },
    "jadwal": [
      {
        "tanggal": "Senin, 01/05/2023",
        "imsak": "04:55",
        "subuh": "05:05",
        "terbit": "06:20",
        "dhuha": "06:48",
        "dzuhur": "12:36",
        "ashar": "15:52",
        "maghrib": "18:44",
        "isya": "19:56",
        "date": "2023-05-01"
      },
      {
        "tanggal": "Selasa, 02/05/2023",
        "imsak": "04:55",
        "subuh": "05:05",
        "terbit": "06:20",
        "dhuha": "06:48",
        "dzuhur": "12:36",
        "ashar": "15:53",
        "maghrib": "18:44",
        "isya": "19:56",
        "date": "2023-05-02"
      },
      {
        "tanggal": "Rabu, 03/05/2023",
        "imsak": "04:55",
        "subuh": "05:05",
        "terbit": "06:19",
        "dhuha": "06:47",
        "dzuhur": "12:35",
        "ashar": "15:53",
        "maghrib": "18:44",
        "isya": "19:56",
        "date": "2023-05-03"
      },
      {
        "tanggal": "Kamis, 04/05/2023",
        "imsak": "04:54",
        "subuh": "05:04",
        "terbit": "06:19",
        "dhuha": "06:47",
        "dzuhur": "12:35",
        "ashar": "15:53",
        "maghrib": "18:44",
        "isya": "19:56",
        "date": "2023-05-04"
      },
      {
        "tanggal": "Jumat, 05/05/2023",
        "imsak": "04:54",
        "subuh": "05:04",
        "terbit": "06:19",
        "dhuha": "06:47",
        "dzuhur": "12:35",
        "ashar": "15:53",
        "maghrib": "18:44",
        "isya": "19:56",
        "date": "2023-05-05"
      },
      {
        "tanggal": "Sabtu, 06/05/2023",
        "imsak": "04:54",
        "subuh": "05:04",
        "terbit": "06:19",
        "dhuha": "06:47",
        "dzuhur": "12:35",
        "ashar": "15:54",
        "maghrib": "18:45",
        "isya": "19:56",
        "date": "2023-05-06"
      },
      {
        "tanggal": "Minggu, 07/05/2023",
        "imsak": "04:53",
        "subuh": "05:03",
        "terbit": "06:19",
        "dhuha": "06:47",
        "dzuhur": "12:35",
        "ashar": "15:54",
        "maghrib": "18:45",
        "isya": "19:56",
        "date": "2023-05-07"
      },
      {
        "tanggal": "Senin, 08/05/2023",
        "imsak": "04:53",
        "subuh": "05:03",
        "terbit": "06:18",
        "dhuha": "06:46",
        "dzuhur": "12:35",
        "ashar": "15:54",
        "maghrib": "18:45",
        "isya": "19:57",
        "date": "2023-05-08"
      },
      {
        "tanggal": "Selasa, 09/05/2023",
        "imsak": "04:53",
        "subuh": "05:03",
        "terbit": "06:18",
        "dhuha": "06:46",
        "dzuhur": "12:35",
        "ashar": "15:55",
        "maghrib": "18:45",
        "isya": "19:57",
        "date": "2023-05-09"
      },
      {
        "tanggal": "Rabu, 10/05/2023",
        "imsak": "04:52",
        "subuh": "05:02",
        "terbit": "06:18",
        "dhuha": "06:46",
        "dzuhur": "12:35",
        "ashar": "15:55",
        "maghrib": "18:45",
        "isya": "19:57",
        "date": "2023-05-10"
      },
      {
        "tanggal": "Kamis, 11/05/2023",
        "imsak": "04:52",
        "subuh": "05:02",
        "terbit": "06:18",
        "dhuha": "06:46",
        "dzuhur": "12:35",
        "ashar": "15:55",
        "maghrib": "18:45",
        "isya": "19:57",
        "date": "2023-05-11"
      },
      {
        "tanggal": "Jumat, 12/05/2023",
        "imsak": "04:52",
        "subuh": "05:02",
        "terbit": "06:18",
        "dhuha": "06:46",
        "dzuhur": "12:35",
        "ashar": "15:55",
        "maghrib": "18:45",
        "isya": "19:57",
        "date": "2023-05-12"
      },
      {
        "tanggal": "Sabtu, 13/05/2023",
        "imsak": "04:52",
        "subuh": "05:02",
        "terbit": "06:18",
        "dhuha": "06:46",
        "dzuhur": "12:35",
        "ashar": "15:56",
        "maghrib": "18:45",
        "isya": "19:58",
        "date": "2023-05-13"
      },
      {
        "tanggal": "Minggu, 14/05/2023",
        "imsak": "04:51",
        "subuh": "05:01",
        "terbit": "06:18",
        "dhuha": "06:46",
        "dzuhur": "12:35",
        "ashar": "15:56",
        "maghrib": "18:45",
        "isya": "19:58",
        "date": "2023-05-14"
      },
      {
        "tanggal": "Senin, 15/05/2023",
        "imsak": "04:51",
        "subuh": "05:01",
        "terbit": "06:17",
        "dhuha": "06:46",
        "dzuhur": "12:35",
        "ashar": "15:56",
        "maghrib": "18:45",
        "isya": "19:58",
        "date": "2023-05-15"
      },
      {
        "tanggal": "Selasa, 16/05/2023",
        "imsak": "04:51",
        "subuh": "05:01",
        "terbit": "06:17",
        "dhuha": "06:46",
        "dzuhur": "12:35",
        "ashar": "15:57",
        "maghrib": "18:45",
        "isya": "19:58",
        "date": "2023-05-16"
      },
      {
        "tanggal": "Rabu, 17/05/2023",
        "imsak": "04:51",
        "subuh": "05:01",
        "terbit": "06:17",
        "dhuha": "06:46",
        "dzuhur": "12:35",
        "ashar": "15:57",
        "maghrib": "18:45",
        "isya": "19:59",
        "date": "2023-05-17"
      },
      {
        "tanggal": "Kamis, 18/05/2023",
        "imsak": "04:50",
        "subuh": "05:00",
        "terbit": "06:17",
        "dhuha": "06:46",
        "dzuhur": "12:35",
        "ashar": "15:57",
        "maghrib": "18:46",
        "isya": "19:59",
        "date": "2023-05-18"
      },
      {
        "tanggal": "Jumat, 19/05/2023",
        "imsak": "04:50",
        "subuh": "05:00",
        "terbit": "06:17",
        "dhuha": "06:46",
        "dzuhur": "12:35",
        "ashar": "15:57",
        "maghrib": "18:46",
        "isya": "19:59",
        "date": "2023-05-19"
      },
      {
        "tanggal": "Sabtu, 20/05/2023",
        "imsak": "04:50",
        "subuh": "05:00",
        "terbit": "06:17",
        "dhuha": "06:46",
        "dzuhur": "12:35",
        "ashar": "15:58",
        "maghrib": "18:46",
        "isya": "19:59",
        "date": "2023-05-20"
      },
      {
        "tanggal": "Minggu, 21/05/2023",
        "imsak": "04:50",
        "subuh": "05:00",
        "terbit": "06:17",
        "dhuha": "06:46",
        "dzuhur": "12:35",
        "ashar": "15:58",
        "maghrib": "18:46",
        "isya": "20:00",
        "date": "2023-05-21"
      },
      {
        "tanggal": "Senin, 22/05/2023",
        "imsak": "04:50",
        "subuh": "05:00",
        "terbit": "06:17",
        "dhuha": "06:46",
        "dzuhur": "12:35",
        "ashar": "15:58",
        "maghrib": "18:46",
        "isya": "20:00",
        "date": "2023-05-22"
      },
      {
        "tanggal": "Selasa, 23/05/2023",
        "imsak": "04:50",
        "subuh": "05:00",
        "terbit": "06:17",
        "dhuha": "06:46",
        "dzuhur": "12:35",
        "ashar": "15:59",
        "maghrib": "18:46",
        "isya": "20:00",
        "date": "2023-05-23"
      },
      {
        "tanggal": "Rabu, 24/05/2023",
        "imsak": "04:50",
        "subuh": "05:00",
        "terbit": "06:17",
        "dhuha": "06:46",
        "dzuhur": "12:35",
        "ashar": "15:59",
        "maghrib": "18:47",
        "isya": "20:00",
        "date": "2023-05-24"
      },
      {
        "tanggal": "Kamis, 25/05/2023",
        "imsak": "04:49",
        "subuh": "04:59",
        "terbit": "06:17",
        "dhuha": "06:46",
        "dzuhur": "12:35",
        "ashar": "15:59",
        "maghrib": "18:47",
        "isya": "20:01",
        "date": "2023-05-25"
      },
      {
        "tanggal": "Jumat, 26/05/2023",
        "imsak": "04:49",
        "subuh": "04:59",
        "terbit": "06:17",
        "dhuha": "06:46",
        "dzuhur": "12:35",
        "ashar": "15:59",
        "maghrib": "18:47",
        "isya": "20:01",
        "date": "2023-05-26"
      },
      {
        "tanggal": "Sabtu, 27/05/2023",
        "imsak": "04:49",
        "subuh": "04:59",
        "terbit": "06:17",
        "dhuha": "06:46",
        "dzuhur": "12:36",
        "ashar": "16:00",
        "maghrib": "18:47",
        "isya": "20:01",
        "date": "2023-05-27"
      },
      {
        "tanggal": "Minggu, 28/05/2023",
        "imsak": "04:49",
        "subuh": "04:59",
        "terbit": "06:17",
        "dhuha": "06:46",
        "dzuhur": "12:36",
        "ashar": "16:00",
        "maghrib": "18:47",
        "isya": "20:01",
        "date": "2023-05-28"
      },
      {
        "tanggal": "Senin, 29/05/2023",
        "imsak": "04:49",
        "subuh": "04:59",
        "terbit": "06:17",
        "dhuha": "06:46",
        "dzuhur": "12:36",
        "ashar": "16:00",
        "maghrib": "18:48",
        "isya": "20:02",
        "date": "2023-05-29"
      },
      {
        "tanggal": "Selasa, 30/05/2023",
        "imsak": "04:49",
        "subuh": "04:59",
        "terbit": "06:17",
        "dhuha": "06:46",
        "dzuhur": "12:36",
        "ashar": "16:01",
        "maghrib": "18:48",
        "isya": "20:02",
        "date": "2023-05-30"
      },
      {
        "tanggal": "Rabu, 31/05/2023",
        "imsak": "04:49",
        "subuh": "04:59",
        "terbit": "06:17",
        "dhuha": "06:46",
        "dzuhur": "12:36",
        "ashar": "16:01",
        "maghrib": "18:48",
        "isya": "20:02",
        "date": "2023-05-31"
      }
    ]
  }
}